{
  "Africa Journal (IAI)": { "Publisher":0, "Journal URL":"http://www.internationalafricaninstitute.org/journal.html", "Impact Factor":"1.042", "Five Year IF":0.855, "IF Year":2013, "H Index":0, "Discipline 1":"Area Studies", "Discipline 2":0, "Discipline 3":0, "Discipline 4":0, "Word Count":"", "Date Uploaded":0, "Open Access Status":"No", "Open Access Comments":0, "Water Institute Published Status":"", "Contacts":0, "Additional Comments":0},
  "Journal of Southern African Studies": { "Publisher":0, "Journal URL":"http://www.tandfonline.com/loi/cjss20#.U_3n97ywLOM", "Impact Factor":"0.449", "Five Year IF":0.59, "IF Year":2013, "H Index":20, "Discipline 1":"Area Studies", "Discipline 2":0, "Discipline 3":0, "Discipline 4":0, "Word Count":"Articles= 8500", "Date Uploaded":0, "Open Access Status":"Yes", "Open Access Comments":0, "Water Institute Published Status":"No", "Contacts":0, "Additional Comments":0},
  "AIDS (LWW)": { "Publisher":0, "Journal URL":"http://journals.lww.com/aidsonline/pages/default.aspx", "Impact Factor":"6.557", "Five Year IF":6.13, "IF Year":2013, "H Index":0, "Discipline 1":"Area Studies", "Discipline 2":0, "Discipline 3":0, "Discipline 4":0, "Word Count":"Manuscripts= 3500", "Date Uploaded":0, "Open Access Status":"Yes", "Open Access Comments":0, "Water Institute Published Status":"Yes", "Contacts":0, "Additional Comments":0},
  "Personality and Social Psychology Bulletin": { "Publisher":0, "Journal URL":"http://psp.sagepub.com/", "Impact Factor":"2.515", "Five Year IF":3.52, "IF Year":2013, "H Index":0, "Discipline 1":"Area Studies", "Discipline 2":0, "Discipline 3":0, "Discipline 4":0, "Word Count":"Manuscript (Including abstract= 10000)", "Date Uploaded":0, "Open Access Status":"Yes", "Open Access Comments":0, "Water Institute Published Status":"No", "Contacts":0, "Additional Comments":0},
  "Personality and Social Psychology Review": { "Publisher":0, "Journal URL":"http://psr.sagepub.com/", "Impact Factor":"8.195", "Five Year IF":10.24, "IF Year":2013, "H Index":0, "Discipline 1":"Economic Development ", "Discipline 2":0, "Discipline 3":0, "Discipline 4":0, "Word Count":"Manuscript (Including abstract= 10000)", "Date Uploaded":0, "Open Access Status":"No ", "Open Access Comments":0, "Water Institute Published Status":"No", "Contacts":0, "Additional Comments":0},
  "Environment and Urbanization": { "Publisher":0, "Journal URL":"http://oae.sagepub.com/", "Impact Factor":"1.209", "Five Year IF":2.292, "IF Year":2013, "H Index":0, "Discipline 1":"Economic Development ", "Discipline 2":0, "Discipline 3":0, "Discipline 4":0, "Word Count":"Book reviews= 1,575", "Date Uploaded":0, "Open Access Status":"Yes", "Open Access Comments":0, "Water Institute Published Status":"No", "Contacts":0, "Additional Comments":0},
  "Journal of Development Economics": { "Publisher":0, "Journal URL":"http://www.journals.elsevier.com/journal-of-development-economics/", "Impact Factor":"2.411", "Five Year IF":2.92, "IF Year":2013, "H Index":0, "Discipline 1":"Economic Development ", "Discipline 2":0, "Discipline 3":0, "Discipline 4":0, "Word Count":"Articles= 600", "Date Uploaded":0, "Open Access Status":"Yes", "Open Access Comments":0, "Water Institute Published Status":"No", "Contacts":0, "Additional Comments":0},
  "Journal of Development Studies": { "Publisher":0, "Journal URL":"http://www.tandfonline.com/loi/fjds20#.U_3lp7ywLOM", "Impact Factor":"0.714", "Five Year IF":1.21, "IF Year":2013, "H Index":0, "Discipline 1":"Economic Development ", "Discipline 2":0, "Discipline 3":0, "Discipline 4":0, "Word Count":"Manuscript= 1000", "Date Uploaded":0, "Open Access Status":"Yes", "Open Access Comments":0, "Water Institute Published Status":"No", "Contacts":0, "Additional Comments":0},
  "Journal of Political Economy": { "Publisher":0, "Journal URL":"http://www.press.uchicago.edu/ucp/journals/journal/jpe.html", "Impact Factor":"3.617", "Five Year IF":5.42, "IF Year":2013, "H Index":96, "Discipline 1":"Economic Development ", "Discipline 2":0, "Discipline 3":0, "Discipline 4":0, "Word Count":"", "Date Uploaded":0, "Open Access Status":"Yes", "Open Access Comments":0, "Water Institute Published Status":"No", "Contacts":0, "Additional Comments":0},
  "Journal of the European Economic Association": { "Publisher":0, "Journal URL":"http://onlinelibrary.wiley.com/journal/10.1111/(ISSN)1542-4774", "Impact Factor":"3.356", "Five Year IF":1.97, "IF Year":2013, "H Index":0, "Discipline 1":"Economic Development ", "Discipline 2":0, "Discipline 3":0, "Discipline 4":0, "Word Count":"Abstracts= 250", "Date Uploaded":0, "Open Access Status":"No", "Open Access Comments":0, "Water Institute Published Status":"No", "Contacts":0, "Additional Comments":0},
  "The World Bank Economic Review": { "Publisher":0, "Journal URL":"http://wber.oxfordjournals.org/", "Impact Factor":"1.095", "Five Year IF":2.48, "IF Year":2013, "H Index":0, "Discipline 1":"Economic Development ", "Discipline 2":0, "Discipline 3":0, "Discipline 4":0, "Word Count":"", "Date Uploaded":0, "Open Access Status":"Yes", "Open Access Comments":0, "Water Institute Published Status":"No", "Contacts":0, "Additional Comments":0},
  "Cochrane Review": { "Publisher":0, "Journal URL":"http://www.cochrane.org/", "Impact Factor":"5.939", "Five Year IF":6.51, "IF Year":2013, "H Index":0, "Discipline 1":"Economic Development ", "Discipline 2":0, "Discipline 3":0, "Discipline 4":0, "Word Count":"Review= 10000, abstracts 1000", "Date Uploaded":0, "Open Access Status":"Yes", "Open Access Comments":0, "Water Institute Published Status":"No", "Contacts":0, "Additional Comments":0},
  "The World Bank Research Observer": { "Publisher":0, "Journal URL":"http://wbro.oxfordjournals.org/", "Impact Factor":"2.1", "Five Year IF":1.84, "IF Year":2013, "H Index":0, "Discipline 1":"Economic Development And Cultural Change", "Discipline 2":0, "Discipline 3":0, "Discipline 4":0, "Word Count":"", "Date Uploaded":0, "Open Access Status":"Yes", "Open Access Comments":0, "Water Institute Published Status":"No", "Contacts":0, "Additional Comments":0},
  "World Development (World dev)": { "Publisher":0, "Journal URL":"http://www.journals.elsevier.com/world-development/", "Impact Factor":"1.733", "Five Year IF":2.18, "IF Year":2013, "H Index":0, "Discipline 1":"Economic Development And Cultural Change", "Discipline 2":0, "Discipline 3":0, "Discipline 4":0, "Word Count":"Manuscript= 10000 abstract= 100", "Date Uploaded":0, "Open Access Status":"Yes", "Open Access Comments":0, "Water Institute Published Status":"No", "Contacts":0, "Additional Comments":0},
  "Economic Development and Cultural Change": { "Publisher":0, "Journal URL":"http://www.press.uchicago.edu/ucp/journals/journal/edcc.html", "Impact Factor":"0.868", "Five Year IF":1.45, "IF Year":2013, "H Index":34, "Discipline 1":"Engineering/Environmental Science ", "Discipline 2":0, "Discipline 3":0, "Discipline 4":0, "Word Count":"Articles= 200", "Date Uploaded":0, "Open Access Status":"No", "Open Access Comments":0, "Water Institute Published Status":"No", "Contacts":0, "Additional Comments":0},
  "Urban Studies": { "Publisher":0, "Journal URL":"http://usj.sagepub.com/", "Impact Factor":"1.493", "Five Year IF":1.98, "IF Year":2013, "H Index":66, "Discipline 1":"Engineering/Environmental Science ", "Discipline 2":0, "Discipline 3":0, "Discipline 4":0, "Word Count":"", "Date Uploaded":0, "Open Access Status":"Yes", "Open Access Comments":0, "Water Institute Published Status":"No", "Contacts":0, "Additional Comments":0},
  "AMBIO": { "Publisher":0, "Journal URL":"http://www.springer.com/environment/journal/13280", "Impact Factor":"2.973", "Five Year IF":3.248, "IF Year":2013, "H Index":0, "Discipline 1":"Engineering/Environmental Science ", "Discipline 2":0, "Discipline 3":0, "Discipline 4":0, "Word Count":"Report=6000 Review= 9000 Perspective=6000 Comment=1000", "Date Uploaded":0, "Open Access Status":"Yes", "Open Access Comments":0, "Water Institute Published Status":"", "Contacts":0, "Additional Comments":0},
  "Annual Review of Environment and Resources": { "Publisher":0, "Journal URL":"http://www.annualreviews.org/journal/energy", "Impact Factor":"5.056", "Five Year IF":7.25, "IF Year":2013, "H Index":0, "Discipline 1":"Engineering/Environmental Science ", "Discipline 2":0, "Discipline 3":0, "Discipline 4":0, "Word Count":"Abstracts= 150", "Date Uploaded":0, "Open Access Status":"Yes", "Open Access Comments":0, "Water Institute Published Status":"No", "Contacts":0, "Additional Comments":0},
  "Journal of Environmental Science and Health Part A Toxic/Hazardous Substances ": { "Publisher":0, "Journal URL":"http://www.tandfonline.com/loi/lesa20#.U_33_rywLOM", "Impact Factor":"1.135", "Five Year IF":0, "IF Year":2013, "H Index":0, "Discipline 1":"Engineering/Environmental Science ", "Discipline 2":0, "Discipline 3":0, "Discipline 4":0, "Word Count":"Not specified", "Date Uploaded":0, "Open Access Status":"Yes", "Open Access Comments":0, "Water Institute Published Status":"Yes", "Contacts":0, "Additional Comments":0},
  "Journal of Urban Planning and Development-ASCE": { "Publisher":0, "Journal URL":"http://ascelibrary.org/journal/jupddm", "Impact Factor":"0.931", "Five Year IF":1.173, "IF Year":2013, "H Index":0, "Discipline 1":"Engineering/Environmental Science ", "Discipline 2":0, "Discipline 3":0, "Discipline 4":0, "Word Count":"manuscripts= 10,000", "Date Uploaded":0, "Open Access Status":"No", "Open Access Comments":0, "Water Institute Published Status":"No", "Contacts":0, "Additional Comments":0},
  "Water Research": { "Publisher":0, "Journal URL":"http://www.journals.elsevier.com/water-research/", "Impact Factor":"5.323", "Five Year IF":5.389, "IF Year":2013, "H Index":145, "Discipline 1":"Environmental Policy", "Discipline 2":0, "Discipline 3":0, "Discipline 4":0, "Word Count":"Manuscript= 8000", "Date Uploaded":0, "Open Access Status":"Yes", "Open Access Comments":0, "Water Institute Published Status":"No", "Contacts":0, "Additional Comments":0},
  "Environmental Engineering Science": { "Publisher":0, "Journal URL":"http://www.liebertpub.com/overview/environmental-engineering-science/15/", "Impact Factor":"0.933", "Five Year IF":1.19, "IF Year":2012, "H Index":0, "Discipline 1":"Environmental Policy", "Discipline 2":0, "Discipline 3":0, "Discipline 4":0, "Word Count":"Manuscript= 8000", "Date Uploaded":0, "Open Access Status":"Yes", "Open Access Comments":0, "Water Institute Published Status":"No", "Contacts":0, "Additional Comments":0},
  "Water Science and Technology": { "Publisher":0, "Journal URL":"http://www.iwaponline.com/wst/", "Impact Factor":"1.212", "Five Year IF":1.146, "IF Year":2013, "H Index":81, "Discipline 1":"Environmental Policy", "Discipline 2":0, "Discipline 3":0, "Discipline 4":0, "Word Count":"Manuscript= 8000 abstract= 200", "Date Uploaded":0, "Open Access Status":"Yes", "Open Access Comments":0, "Water Institute Published Status":"Yes", "Contacts":Roisin Rooney, Associate Editor, "Additional Comments":0},
  "Environmental Monitoring and Assessment": { "Publisher":0, "Journal URL":"http://link.springer.com/journal/10661", "Impact Factor":"1.679", "Five Year IF":1.79, "IF Year":2013, "H Index":0, "Discipline 1":"Environmental Policy ", "Discipline 2":0, "Discipline 3":0, "Discipline 4":0, "Word Count":"Abstract= 250", "Date Uploaded":0, "Open Access Status":"Yes", "Open Access Comments":0, "Water Institute Published Status":"Yes", "Contacts":0, "Additional Comments":0},
  "Global Environmental Change": { "Publisher":0, "Journal URL":"http://www.journals.elsevier.com/global-environmental-change/", "Impact Factor":"6", "Five Year IF":6.901, "IF Year":2013, "H Index":60, "Discipline 1":"Environmental Policy ", "Discipline 2":0, "Discipline 3":0, "Discipline 4":0, "Word Count":"N/A", "Date Uploaded":0, "Open Access Status":"Yes", "Open Access Comments":0, "Water Institute Published Status":"No", "Contacts":0, "Additional Comments":0},
  "Journal of Environmental Economics and Management": { "Publisher":0, "Journal URL":"http://www.journals.elsevier.com/journal-of-environmental-economics-and-management/", "Impact Factor":"2.522", "Five Year IF":3.06, "IF Year":2013, "H Index":4, "Discipline 1":"Environmental Policy ", "Discipline 2":0, "Discipline 3":0, "Discipline 4":0, "Word Count":"Abstracts= 150", "Date Uploaded":0, "Open Access Status":"Yes", "Open Access Comments":0, "Water Institute Published Status":"No", "Contacts":0, "Additional Comments":0},
  "Environmental Science and Policy": { "Publisher":0, "Journal URL":"http://www.journals.elsevier.com/environmental-science-and-policy/", "Impact Factor":"3.514", "Five Year IF":3.461, "IF Year":2013, "H Index":38, "Discipline 1":"Environmental Policy And Management", "Discipline 2":Environmental Sciences, "Discipline 3":0, "Discipline 4":0, "Word Count":"Research letter= 4000", "Date Uploaded":0, "Open Access Status":"Yes", "Open Access Comments":0, "Water Institute Published Status":"No", "Contacts":0, "Additional Comments":0},
  "Environmental Science and Technology": { "Publisher":0, "Journal URL":"http://pubs.acs.org/journal/esthag", "Impact Factor":"5.481", "Five Year IF":5.865, "IF Year":2013, "H Index":197, "Discipline 1":"Environmental Policy And Management", "Discipline 2":Environmental Sciences, "Discipline 3":Environmental Policy And Management, "Discipline 4":0, "Word Count":"Research letter= 4000", "Date Uploaded":0, "Open Access Status":"Yes", "Open Access Comments":0, "Water Institute Published Status":"Yes", "Contacts":0, "Additional Comments":0},
  "Journal of Environmental Policy and Planning": { "Publisher":0, "Journal URL":"http://www.tandfonline.com/loi/cjoe20#.U_3mELywLOM", "Impact Factor":"1.279", "Five Year IF":0?, "IF Year":2013, "H Index":21, "Discipline 1":"Environmental Policy And Management", "Discipline 2":0, "Discipline 3":0, "Discipline 4":0, "Word Count":"Research paper= 9000 abstract 100", "Date Uploaded":0, "Open Access Status":"Yes", "Open Access Comments":0, "Water Institute Published Status":"No", "Contacts":0, "Additional Comments":0},
  "Journal of Environmental Quality": { "Publisher":0, "Journal URL":"https://www.agronomy.org/publications/jeq", "Impact Factor":"2.345", "Five Year IF":2.6, "IF Year":2013, "H Index":0, "Discipline 1":"Environmental Policy And Management", "Discipline 2":0, "Discipline 3":0, "Discipline 4":0, "Word Count":"Abstract= 250", "Date Uploaded":0, "Open Access Status":"Yes", "Open Access Comments":0, "Water Institute Published Status":"Yes", "Contacts":0, "Additional Comments":0},
  "Development Policy Review": { "Publisher":0, "Journal URL":"http://onlinelibrary.wiley.com/journal/10.1111/(ISSN)1467-7679", "Impact Factor":"0.861", "Five Year IF":1.73, "IF Year":2013, "H Index":0, "Discipline 1":"Environmental Policy And Management", "Discipline 2":0, "Discipline 3":0, "Discipline 4":0, "Word Count":"Articles= 10.000", "Date Uploaded":0, "Open Access Status":"Yes", "Open Access Comments":0, "Water Institute Published Status":"No", "Contacts":0, "Additional Comments":0},
  "Ecology and Society": { "Publisher":0, "Journal URL":"http://www.ecologyandsociety.org/", "Impact Factor":"2.669", "Five Year IF":3.681, "IF Year":2013, "H Index":0, "Discipline 1":"Environmental Sciences", "Discipline 2":0, "Discipline 3":0, "Discipline 4":0, "Word Count":"Core article= 5000", "Date Uploaded":0, "Open Access Status":"Yes", "Open Access Comments":0, "Water Institute Published Status":"No", "Contacts":0, "Additional Comments":0},
  "Environmental and Resource Economics": { "Publisher":0, "Journal URL":"http://www.springer.com/economics/environmental/journal/10640", "Impact Factor":"1.703", "Five Year IF":1.71, "IF Year":2013, "H Index":0, "Discipline 1":"Environmental Sciences", "Discipline 2":0, "Discipline 3":0, "Discipline 4":0, "Word Count":"Abstract= 200", "Date Uploaded":0, "Open Access Status":"Yes", "Open Access Comments":0, "Water Institute Published Status":"No", "Contacts":0, "Additional Comments":0},
  "Environmental Politics": { "Publisher":0, "Journal URL":"http://www.tandfonline.com/loi/fenp20#.U_3j1LywLOM", "Impact Factor":"1.64", "Five Year IF":1.814, "IF Year":2013, "H Index":28, "Discipline 1":"Environmental Sciences", "Discipline 2":0, "Discipline 3":0, "Discipline 4":0, "Word Count":"Articles= 8000", "Date Uploaded":0, "Open Access Status":"Yes", "Open Access Comments":0, "Water Institute Published Status":"No", "Contacts":0, "Additional Comments":0},
  "Organization and Environment": { "Publisher":0, "Journal URL":"1http://oae.sagepub.com/", "Impact Factor":"1.209", "Five Year IF":1.53, "IF Year":2013, "H Index":22, "Discipline 1":"Environmental Sciences", "Discipline 2":0, "Discipline 3":0, "Discipline 4":0, "Word Count":"Abstract= 250", "Date Uploaded":0, "Open Access Status":"Yes", "Open Access Comments":0, "Water Institute Published Status":"No", "Contacts":0, "Additional Comments":0},
  "CRITICAL REVIEWS IN ENVIRONMENTAL SCIENCE AND TECHNOLOGY": { "Publisher":0, "Journal URL":"http://www.tandfonline.com/loi/best20#.U_3jM7ywLOM", "Impact Factor":"3.238", "Five Year IF":5.364, "IF Year":2013, "H Index":0, "Discipline 1":"Environmental Sciences", "Discipline 2":0, "Discipline 3":0, "Discipline 4":0, "Word Count":"Article= 6000", "Date Uploaded":0, "Open Access Status":"Yes", "Open Access Comments":0, "Water Institute Published Status":"No", "Contacts":0, "Additional Comments":0},
  "Environmental Research Letters": { "Publisher":0, "Journal URL":"http://iopscience.iop.org/1748-9326/", "Impact Factor":"4.09", "Five Year IF":4.281, "IF Year":2013, "H Index":27, "Discipline 1":"Environmental Sciences", "Discipline 2":0, "Discipline 3":0, "Discipline 4":0, "Word Count":"Research letter= 4000", "Date Uploaded":0, "Open Access Status":"Yes", "Open Access Comments":0, "Water Institute Published Status":"No", "Contacts":0, "Additional Comments":Open Access},
  "Environmental Technology": { "Publisher":0, "Journal URL":"http://www.tandfonline.com/loi/tent20#.U_32RLywLOM", "Impact Factor":"1.197", "Five Year IF":1.36, "IF Year":2013, "H Index":0, "Discipline 1":"Health And Human Rights", "Discipline 2":0, "Discipline 3":0, "Discipline 4":0, "Word Count":"Manuscripts= 6000", "Date Uploaded":0, "Open Access Status":"No", "Open Access Comments":0, "Water Institute Published Status":"Yes", "Contacts":0, "Additional Comments":0},
  "Journal of Environmental Science and Health Part A (J ENVIRON SCI HEAL)": { "Publisher":0, "Journal URL":"http://www.tandfonline.com/loi/lesa20#.U_3337ywLOM", "Impact Factor":"1.19", "Five Year IF":1.32, "IF Year":2013, "H Index":0, "Discipline 1":"Health And Human Rights", "Discipline 2":0, "Discipline 3":0, "Discipline 4":0, "Word Count":"Not specified", "Date Uploaded":0, "Open Access Status":"Yes", "Open Access Comments":0, "Water Institute Published Status":"Yes", "Contacts":0, "Additional Comments":0},
  "Natural Resources Forum": { "Publisher":0, "Journal URL":"http://onlinelibrary.wiley.com/journal/10.1111/(ISSN)1477-8947", "Impact Factor":"1", "Five Year IF":1.28, "IF Year":2013, "H Index":0, "Discipline 1":"Health And Human Rights", "Discipline 2":0, "Discipline 3":0, "Discipline 4":0, "Word Count":"Manuscript= 8000 abstract= 200", "Date Uploaded":0, "Open Access Status":"Yes", "Open Access Comments":0, "Water Institute Published Status":"No", "Contacts":0, "Additional Comments":0},
  "Nature Climate Change": { "Publisher":0, "Journal URL":"http://www.nature.com/nclimate/index.html", "Impact Factor":"15.295", "Five Year IF":14.5, "IF Year":2013, "H Index":0, "Discipline 1":"International Development", "Discipline 2":0, "Discipline 3":0, "Discipline 4":0, "Word Count":"Abstracts= 150 Article= 6000", "Date Uploaded":0, "Open Access Status":"Yes", "Open Access Comments":0, "Water Institute Published Status":"No", "Contacts":0, "Additional Comments":0},
  "BMC International Health and Human Rights": { "Publisher":0, "Journal URL":"http://www.biomedcentral.com/bmcinthealthhumrights/", "Impact Factor":"1.1", "Five Year IF":0?, "IF Year":2013, "H Index":14, "Discipline 1":"International Development", "Discipline 2":0, "Discipline 3":0, "Discipline 4":0, "Word Count":"Abstracts= 350", "Date Uploaded":0, "Open Access Status":"Yes", "Open Access Comments":0, "Water Institute Published Status":"No", "Contacts":0, "Additional Comments":0},
  "Journal of Human Development AND CAPABILITIES": { "Publisher":0, "Journal URL":"http://www.tandfonline.com/loi/cjhd20#.U_3mwrywLOM", "Impact Factor":"0.729", "Five Year IF":0?, "IF Year":2013, "H Index":0, "Discipline 1":"International Development", "Discipline 2":0, "Discipline 3":0, "Discipline 4":0, "Word Count":"Review= 8000 abstract= 200", "Date Uploaded":0, "Open Access Status":"Yes", "Open Access Comments":0, "Water Institute Published Status":"No", "Contacts":0, "Additional Comments":Hybrid open access option},
  "Journal of Human Rights Practice": { "Publisher":0, "Journal URL":"http://jhrp.oxfordjournals.org/", "Impact Factor":"N/A", "Five Year IF":o?, "IF Year":2013, "H Index":3, "Discipline 1":"International Development", "Discipline 2":0, "Discipline 3":0, "Discipline 4":0, "Word Count":"Articles= 10,000, comments= 1200", "Date Uploaded":0, "Open Access Status":"Yes", "Open Access Comments":0, "Water Institute Published Status":"Yes", "Contacts":0, "Additional Comments":0},
  "Development in Practice": { "Publisher":0, "Journal URL":"http://www.developmentinpractice.org/", "Impact Factor":"N/A", "Five Year IF":0, "IF Year":2013, "H Index":17, "Discipline 1":"International Development", "Discipline 2":0, "Discipline 3":0, "Discipline 4":0, "Word Count":"", "Date Uploaded":0, "Open Access Status":"Yes", "Open Access Comments":0, "Water Institute Published Status":"No", "Contacts":0, "Additional Comments":0},
  "Developmental Studies Research": { "Publisher":0, "Journal URL":"http://www.tandfonline.com/loi/rdsr20#.U_3jZ7ywLOM", "Impact Factor":"N/A", "Five Year IF":1.21, "IF Year":2013, "H Index":0, "Discipline 1":"International Development", "Discipline 2":Policy And Practice, "Discipline 3":Theory, "Discipline 4":0, "Word Count":"Articles= 10,000", "Date Uploaded":0, "Open Access Status":"Yes", "Open Access Comments":0, "Water Institute Published Status":"No", "Contacts":0, "Additional Comments":Open access},
  "International Development Planning Review": { "Publisher":0, "Journal URL":"http://www.liverpooluniversitypress.co.uk/index.php?option=com_content&view=article&id=51:international-development-planning-review&catid=8", "Impact Factor":"N/A", "Five Year IF":0.66, "IF Year":2013, "H Index":12, "Discipline 1":"International Development", "Discipline 2":0, "Discipline 3":0, "Discipline 4":0, "Word Count":"Research letter= 6000", "Date Uploaded":0, "Open Access Status":"Yes", "Open Access Comments":0, "Water Institute Published Status":"No", "Contacts":0, "Additional Comments":0},
  "Journal of Environmental Engineering-ASCE": { "Publisher":0, "Journal URL":"http://ascelibrary.org/journal/joeedu", "Impact Factor":"1.221", "Five Year IF":1.507, "IF Year":2013, "H Index":0, "Discipline 1":"International Development", "Discipline 2":Environmental Sciences, "Discipline 3":0, "Discipline 4":0, "Word Count":"manuscripts= 10,000 comments= 3500 ", "Date Uploaded":0, "Open Access Status":"Yes", "Open Access Comments":0, "Water Institute Published Status":"No", "Contacts":0, "Additional Comments":0},
  "International Health": { "Publisher":0, "Journal URL":"http://inthealth.oxfordjournals.org/", "Impact Factor":"1.129", "Five Year IF":1.009, "IF Year":2013, "H Index":5, "Discipline 1":"International Development", "Discipline 2":0, "Discipline 3":0, "Discipline 4":0, "Word Count":"Manuscript= 7000", "Date Uploaded":0, "Open Access Status":"Yes", "Open Access Comments":0, "Water Institute Published Status":"No", "Contacts":0, "Additional Comments":0},
  "International Journal of Environmental Science and Technology": { "Publisher":0, "Journal URL":"http://www.springer.com/environment/journal/13762", "Impact Factor":"1.794", "Five Year IF":1.984, "IF Year":2013, "H Index":0, "Discipline 1":"International Development", "Discipline 2":0, "Discipline 3":0, "Discipline 4":0, "Word Count":"No limits, manuscripts and results size= 10", "Date Uploaded":0, "Open Access Status":"Yes", "Open Access Comments":0, "Water Institute Published Status":"No", "Contacts":0, "Additional Comments":0},
  "International Journal of Epidemiology": { "Publisher":0, "Journal URL":"http://ije.oxfordjournals.org/", "Impact Factor":"9.197", "Five Year IF":7.001, "IF Year":2013, "H Index":0, "Discipline 1":"International Development/ Public Health", "Discipline 2":0, "Discipline 3":0, "Discipline 4":0, "Word Count":"manuscripts= 3000, reviews= 6000", "Date Uploaded":0, "Open Access Status":"Yes", "Open Access Comments":0, "Water Institute Published Status":"No", "Contacts":0, "Additional Comments":0},
  "International Journal of Water Resources Development": { "Publisher":0, "Journal URL":"http://www.tandfonline.com/loi/cijw20#.U_3lwbywLOM", "Impact Factor":"0.895", "Five Year IF":0.991, "IF Year":2013, "H Index":0, "Discipline 1":"International Development/ Public Health", "Discipline 2":0, "Discipline 3":0, "Discipline 4":0, "Word Count":"", "Date Uploaded":0, "Open Access Status":"Yes", "Open Access Comments":0, "Water Institute Published Status":"No", "Contacts":0, "Additional Comments":0},
  "Journal of Health Communication": { "Publisher":0, "Journal URL":"http://www.tandfonline.com/loi/uhcm20#.U_3mJLywLOM", "Impact Factor":"1.869", "Five Year IF":2.35, "IF Year":2013, "H Index":40, "Discipline 1":"International Development/ Public Health", "Discipline 2":0, "Discipline 3":0, "Discipline 4":0, "Word Count":"articles= 5000 abstract= 200", "Date Uploaded":0, "Open Access Status":"Yes", "Open Access Comments":0, "Water Institute Published Status":"No", "Contacts":0, "Additional Comments":0},
  "Journal of Health Population and Nutrition": { "Publisher":0, "Journal URL":"http://www.jhpn.net/", "Impact Factor":"1.388", "Five Year IF":1.31, "IF Year":2013, "H Index":0, "Discipline 1":"Life, Biomedical, And Environmental Sciences", "Discipline 2":0, "Discipline 3":0, "Discipline 4":0, "Word Count":"Review article= 8500", "Date Uploaded":0, "Open Access Status":"Yes", "Open Access Comments":0, "Water Institute Published Status":"No", "Contacts":0, "Additional Comments":0},
  "Journal of Environment and Development": { "Publisher":0, "Journal URL":"http://jed.sagepub.com/", "Impact Factor":"1.606", "Five Year IF":0, "IF Year":2013, "H Index":39, "Discipline 1":"Prevention And Control Of Tropical Disease", "Discipline 2":0, "Discipline 3":0, "Discipline 4":0, "Word Count":"Manuscript= 8000, abstract= 250", "Date Uploaded":0, "Open Access Status":"Yes", "Open Access Comments":0, "Water Institute Published Status":"No", "Contacts":0, "Additional Comments":0},
  "Journal of International Development": { "Publisher":0, "Journal URL":"http://onlinelibrary.wiley.com/journal/10.1002/(ISSN)1099-1328", "Impact Factor":"0.669", "Five Year IF":0, "IF Year":2013, "H Index":0, "Discipline 1":"Public Health", "Discipline 2":0, "Discipline 3":0, "Discipline 4":0, "Word Count":"Abstract= 100", "Date Uploaded":0, "Open Access Status":"Yes", "Open Access Comments":0, "Water Institute Published Status":"No", "Contacts":0, "Additional Comments":0},
  "Third World Quarterly": { "Publisher":0, "Journal URL":"http://www.tandfonline.com/loi/ctwq20#.U_3dGLywLOM", "Impact Factor":"0.704", "Five Year IF":0.94, "IF Year":2013, "H Index":30, "Discipline 1":"Public Health", "Discipline 2":0, "Discipline 3":0, "Discipline 4":0, "Word Count":"Manuscript= 8000 abstract= 150", "Date Uploaded":0, "Open Access Status":"No ", "Open Access Comments":0, "Water Institute Published Status":"No", "Contacts":0, "Additional Comments":0},
  "Environment Development and Sustainability ": { "Publisher":0, "Journal URL":"http://www.springer.com/environment/sustainable+development/journal/10668", "Impact Factor":"N/A", "Five Year IF":0, "IF Year":2013, "H Index":0, "Discipline 1":"Public Health", "Discipline 2":0, "Discipline 3":0, "Discipline 4":0, "Word Count":"Abstract= 250", "Date Uploaded":0, "Open Access Status":"Yes", "Open Access Comments":0, "Water Institute Published Status":"No", "Contacts":0, "Additional Comments":0},
  "Journal of Microbiological Methods": { "Publisher":0, "Journal URL":"http://www.journals.elsevier.com/journal-of-microbiological-methods/", "Impact Factor":"2.096", "Five Year IF":2.51, "IF Year":2013, "H Index":0, "Discipline 1":"Public Health", "Discipline 2":0, "Discipline 3":0, "Discipline 4":0, "Word Count":"Abstracts= 50", "Date Uploaded":0, "Open Access Status":"Yes", "Open Access Comments":0, "Water Institute Published Status":"Yes", "Contacts":0, "Additional Comments":0},
  "PLOS Neglected Tropical Diseases": { "Publisher":0, "Journal URL":"http://journals.plos.org/plosntds/", "Impact Factor":"4.489", "Five Year IF":4.963, "IF Year":2013, "H Index":0, "Discipline 1":"Public Health", "Discipline 2":0, "Discipline 3":0, "Discipline 4":0, "Word Count":"research article= 3001", "Date Uploaded":0, "Open Access Status":"Yes", "Open Access Comments":0, "Water Institute Published Status":"Yes", "Contacts":0, "Additional Comments":0},
  "Sustainability": { "Publisher":0, "Journal URL":"http://www.mdpi.com/journal/sustainability", "Impact Factor":"1.077", "Five Year IF":0, "IF Year":2013, "H Index":0, "Discipline 1":"Public Health", "Discipline 2":0, "Discipline 3":0, "Discipline 4":0, "Word Count":"Abstract= 200", "Date Uploaded":0, "Open Access Status":"Yes", "Open Access Comments":0, "Water Institute Published Status":"No", "Contacts":0, "Additional Comments":0},
  "Scientific Data (Nature)": { "Publisher":0, "Journal URL":"http://www.nature.com/sdata/", "Impact Factor":"N/A", "Five Year IF":0, "IF Year":2013, "H Index":0, "Discipline 1":"Public Health", "Discipline 2":0, "Discipline 3":0, "Discipline 4":0, "Word Count":"", "Date Uploaded":0, "Open Access Status":"No", "Open Access Comments":0, "Water Institute Published Status":"No", "Contacts":0, "Additional Comments":Open access, online only. New; currently calling for submissions and will launch May 2014},
  "American Journal of Tropical Med and Hygiene": { "Publisher":0, "Journal URL":"http://www.ajtmh.org/", "Impact Factor":"2.736", "Five Year IF":2.896, "IF Year":2013, "H Index":0, "Discipline 1":"Public Health", "Discipline 2":0, "Discipline 3":0, "Discipline 4":0, "Word Count":"Research letter= 1500", "Date Uploaded":0, "Open Access Status":"Yes", "Open Access Comments":0, "Water Institute Published Status":"Yes", "Contacts":0, "Additional Comments":Fast turn around},
  "Bulletin of the WHO": { "Publisher":0, "Journal URL":"http://www.who.int/bulletin/en/", "Impact Factor":"5.112", "Five Year IF":6.076, "IF Year":2013, "H Index":0, "Discipline 1":"Public Health", "Discipline 2":0, "Discipline 3":0, "Discipline 4":0, "Word Count":"Analytical assesments= 3000 perspetices= 1500 ", "Date Uploaded":0, "Open Access Status":"Yes", "Open Access Comments":0, "Water Institute Published Status":"No", "Contacts":0, "Additional Comments":0},
  "Bulletin of the World Health Organization": { "Publisher":0, "Journal URL":"http://www.who.int/bulletin/en/", "Impact Factor":"5.112", "Five Year IF":6.08, "IF Year":2013, "H Index":0, "Discipline 1":"Public Health", "Discipline 2":0, "Discipline 3":0, "Discipline 4":0, "Word Count":"Research article= 3000 ", "Date Uploaded":0, "Open Access Status":"Yes", "Open Access Comments":0, "Water Institute Published Status":"Yes", "Contacts":0, "Additional Comments":0},
  "Environmental Health Perspectives": { "Publisher":0, "Journal URL":"http://ehp.niehs.nih.gov/", "Impact Factor":"7.03", "Five Year IF":7.522, "IF Year":2013, "H Index":0, "Discipline 1":"Public Health", "Discipline 2":0, "Discipline 3":0, "Discipline 4":0, "Word Count":"Commentaries= 5000", "Date Uploaded":0, "Open Access Status":"Yes", "Open Access Comments":0, "Water Institute Published Status":"No", "Contacts":0, "Additional Comments":0},
  "Epidemiology and Infection": { "Publisher":0, "Journal URL":"http://journals.cambridge.org/action/displayJournal?jid=HYG", "Impact Factor":"2.491", "Five Year IF":2.754, "IF Year":2013, "H Index":0, "Discipline 1":"Public Health", "Discipline 2":Environmental Health, "Discipline 3":Occupational Health, "Discipline 4":0, "Word Count":"research letter= 3000, commentary= 800", "Date Uploaded":0, "Open Access Status":"Yes", "Open Access Comments":0, "Water Institute Published Status":"No", "Contacts":0, "Additional Comments":0},
  "International Journal of Environmental Research and Public Health": { "Publisher":0, "Journal URL":"http://www.mdpi.com/journal/ijerph", "Impact Factor":"1.993", "Five Year IF":0, "IF Year":2013, "H Index":0, "Discipline 1":"Public Health", "Discipline 2":0, "Discipline 3":0, "Discipline 4":0, "Word Count":"Abstract= 200", "Date Uploaded":0, "Open Access Status":"Yes", "Open Access Comments":0, "Water Institute Published Status":"Yes", "Contacts":0, "Additional Comments":0},
  "International Journal of Hygiene and Environmental Health": { "Publisher":0, "Journal URL":"http://www.journals.elsevier.com/international-journal-of-hygiene-and-environmental-health/", "Impact Factor":"3.276", "Five Year IF":3.37, "IF Year":2013, "H Index":0, "Discipline 1":"Public Policy/Administrative Science", "Discipline 2":0, "Discipline 3":0, "Discipline 4":0, "Word Count":"Not specified", "Date Uploaded":0, "Open Access Status":"Yes", "Open Access Comments":0, "Water Institute Published Status":"Yes", "Contacts":0, "Additional Comments":0},
  "Journal of Applied Microbiology": { "Publisher":0, "Journal URL":"http://onlinelibrary.wiley.com/journal/10.1111/(ISSN)1365-2672", "Impact Factor":"2.386", "Five Year IF":2.59, "IF Year":2013, "H Index":0, "Discipline 1":"Public Policy/Administrative Science", "Discipline 2":0, "Discipline 3":0, "Discipline 4":0, "Word Count":"Abstract= 200", "Date Uploaded":0, "Open Access Status":"Yes", "Open Access Comments":0, "Water Institute Published Status":"Yes", "Contacts":0, "Additional Comments":0},
  "Journal of Public Health Policy": { "Publisher":0, "Journal URL":"http://www.palgrave-journals.com/jphp/index.html", "Impact Factor":"1.75", "Five Year IF":2.039, "IF Year":2013, "H Index":0, "Discipline 1":"Public Policy/Administrative Science", "Discipline 2":0, "Discipline 3":0, "Discipline 4":0, "Word Count":"Manuscript= 4000, Abstracts= 150", "Date Uploaded":0, "Open Access Status":"Yes", "Open Access Comments":0, "Water Institute Published Status":"No", "Contacts":0, "Additional Comments":Open access option},
  "New England Journal of Medicine": { "Publisher":0, "Journal URL":"http://www.nejm.org/", "Impact Factor":"55.873", "Five Year IF":54.39, "IF Year":2014, "H Index":0, "Discipline 1":"MEDICINE, GENERAL & INTERNAL", "Discipline 2":0, "Discipline 3":0, "Discipline 4":0, "Word Count":"Research articles= 2700", "Date Uploaded":12/15/15, "Open Access Status":"Yes", "Open Access Comments":Published to web after 6 months, available free to , "Water Institute Published Status":"No", "Contacts":0, "Additional Comments":0},
  "Perspectives in Public Health": { "Publisher":0, "Journal URL":"http://rsh.sagepub.com/", "Impact Factor":"0.981", "Five Year IF":1.11, "IF Year":2013, "H Index":0, "Discipline 1":"Scientific Research", "Discipline 2":0, "Discipline 3":0, "Discipline 4":0, "Word Count":"", "Date Uploaded":0, "Open Access Status":"Yes", "Open Access Comments":0, "Water Institute Published Status":"Yes", "Contacts":0, "Additional Comments":0},
  "PLOS Medicine": { "Publisher":0, "Journal URL":"http://journals.plos.org/plosmedicine/", "Impact Factor":"14", "Five Year IF":16.43, "IF Year":2013, "H Index":0, "Discipline 1":"Scientific Research", "Discipline 2":0, "Discipline 3":0, "Discipline 4":0, "Word Count":"research article= 3000 ", "Date Uploaded":0, "Open Access Status":"Yes", "Open Access Comments":0, "Water Institute Published Status":"Yes", "Contacts":Rhona MacDonals, "Additional Comments":0},
  "Marine pollution bulletin": { "Publisher":0, "Journal URL":"http://www.journals.elsevier.com/marine-pollution-bulletin/", "Impact Factor":"2.793", "Five Year IF":3.08, "IF Year":2013, "H Index":0, "Discipline 1":"Scientific Research", "Discipline 2":0, "Discipline 3":0, "Discipline 4":0, "Word Count":"Abstracts= 150", "Date Uploaded":0, "Open Access Status":"Yes", "Open Access Comments":0, "Water Institute Published Status":"Yes", "Contacts":0, "Additional Comments":0},
  "Tropical Medicine and International Health": { "Publisher":0, "Journal URL":"http://onlinelibrary.wiley.com/journal/10.1111/(ISSN)1365-3156", "Impact Factor":"2.302", "Five Year IF":2.988, "IF Year":2013, "H Index":64, "Discipline 1":"Scientific Research", "Discipline 2":Environmental Health, "Discipline 3":Occupational Health, "Discipline 4":0, "Word Count":"Manuscript= 3500 abstract= 250", "Date Uploaded":0, "Open Access Status":"Yes", "Open Access Comments":0, "Water Institute Published Status":"No", "Contacts":0, "Additional Comments":0},
  "Waterlines": { "Publisher":0, "Journal URL":"http://practicalaction.org/waterlines", "Impact Factor":"N/A", "Five Year IF":0, "IF Year":2013, "H Index":4, "Discipline 1":"Scientific Research", "Discipline 2":Techn And Eng, "Discipline 3":0, "Discipline 4":0, "Word Count":"", "Date Uploaded":0, "Open Access Status":"Yes", "Open Access Comments":0, "Water Institute Published Status":"No", "Contacts":0, "Additional Comments":0},
  "Administrative Science Quarterly": { "Publisher":0, "Journal URL":"http://asq.sagepub.com/", "Impact Factor":"4.182", "Five Year IF":6.55, "IF Year":2013, "H Index":0, "Discipline 1":"Scientific Research", "Discipline 2":0, "Discipline 3":0, "Discipline 4":0, "Word Count":"", "Date Uploaded":0, "Open Access Status":"Yes", "Open Access Comments":0, "Water Institute Published Status":"", "Contacts":0, "Additional Comments":0},
  "Governance: An International Journal of Policy, Administration, and Institutions.": { "Publisher":0, "Journal URL":"http://onlinelibrary.wiley.com/journal/10.1111/(ISSN)1468-0491", "Impact Factor":"1.614", "Five Year IF":1.91, "IF Year":2013, "H Index":0, "Discipline 1":"Scientific Research", "Discipline 2":0, "Discipline 3":0, "Discipline 4":0, "Word Count":"", "Date Uploaded":0, "Open Access Status":"Yes", "Open Access Comments":0, "Water Institute Published Status":"No", "Contacts":0, "Additional Comments":0},
  "Policy Studies Journal": { "Publisher":0, "Journal URL":"http://onlinelibrary.wiley.com/journal/10.1111/(ISSN)1541-0072", "Impact Factor":"2.364", "Five Year IF":1.3, "IF Year":2013, "H Index":23, "Discipline 1":"Water Policy", "Discipline 2":0, "Discipline 3":0, "Discipline 4":0, "Word Count":"Manuscript= 40 pages", "Date Uploaded":0, "Open Access Status":"Yes", "Open Access Comments":0, "Water Institute Published Status":"No", "Contacts":0, "Additional Comments":0},
  "Regulatory Governance": { "Publisher":0, "Journal URL":"http://onlinelibrary.wiley.com/journal/10.1111/(ISSN)1748-5991", "Impact Factor":"1.351", "Five Year IF":1.75, "IF Year":2013, "H Index":0, "Discipline 1":"Water Policy", "Discipline 2":0, "Discipline 3":0, "Discipline 4":0, "Word Count":"Manuscript= 40 pages", "Date Uploaded":0, "Open Access Status":"No", "Open Access Comments":0, "Water Institute Published Status":"No", "Contacts":0, "Additional Comments":0},
  "Applied And Environmental Microbiology": { "Publisher":0, "Journal URL":"http://aem.asm.org/", "Impact Factor":"3.952", "Five Year IF":4.52, "IF Year":2013, "H Index":0, "Discipline 1":"Water Policy", "Discipline 2":0, "Discipline 3":0, "Discipline 4":0, "Word Count":"Abstract= 250", "Date Uploaded":0, "Open Access Status":"Yes", "Open Access Comments":0, "Water Institute Published Status":"Yes", "Contacts":0, "Additional Comments":0},
  "Nature": { "Publisher":0, "Journal URL":"http://www.nature.com/nature/index.html", "Impact Factor":"42.351", "Five Year IF":38.16, "IF Year":2013, "H Index":0, "Discipline 1":"Water Policy", "Discipline 2":0, "Discipline 3":0, "Discipline 4":0, "Word Count":"Abstracts= 150 Article= 3000", "Date Uploaded":0, "Open Access Status":"Yes", "Open Access Comments":0, "Water Institute Published Status":"No", "Contacts":0, "Additional Comments":0},
  "Science": { "Publisher":0, "Journal URL":"http://www.sciencemag.org/magazine", "Impact Factor":"31.477", "Five Year IF":32.45, "IF Year":2013, "H Index":0, "Discipline 1":"Water Policy", "Discipline 2":0, "Discipline 3":0, "Discipline 4":0, "Word Count":"Abstracts= 125", "Date Uploaded":0, "Open Access Status":"Yes", "Open Access Comments":0, "Water Institute Published Status":"No", "Contacts":0, "Additional Comments":0},
  "Social Science and Medicine": { "Publisher":0, "Journal URL":"http://www.journals.elsevier.com/social-science-and-medicine/", "Impact Factor":"2.558", "Five Year IF":3.688, "IF Year":2013, "H Index":0, "Discipline 1":"Water Policy", "Discipline 2":0, "Discipline 3":0, "Discipline 4":0, "Word Count":"Reports= 4000", "Date Uploaded":0, "Open Access Status":"Yes", "Open Access Comments":0, "Water Institute Published Status":"No", "Contacts":0, "Additional Comments":0},
  "The Lancet Infectious Diseases": { "Publisher":0, "Journal URL":"http://www.thelancet.com/journals/laninf/issue/current", "Impact Factor":"N/A", "Five Year IF":18.1, "IF Year":2013, "H Index":0, "Discipline 1":"Water Policy", "Discipline 2":0, "Discipline 3":0, "Discipline 4":0, "Word Count":"research article= 3000 ", "Date Uploaded":0, "Open Access Status":"Yes", "Open Access Comments":0, "Water Institute Published Status":"Yes", "Contacts":0, "Additional Comments":0},
  "Transactions of The Royal Society of Tropical Medicine and Hygiene": { "Publisher":0, "Journal URL":"http://trstmh.oxfordjournals.org/", "Impact Factor":"1.931", "Five Year IF":2.46, "IF Year":2013, "H Index":0, "Discipline 1":"Water Policy", "Discipline 2":0, "Discipline 3":0, "Discipline 4":0, "Word Count":"Research article= 3500 abstract= 200", "Date Uploaded":0, "Open Access Status":"Yes", "Open Access Comments":0, "Water Institute Published Status":"No", "Contacts":0, "Additional Comments":0},
  "Water Resources Research": { "Publisher":0, "Journal URL":"http://agupubs.onlinelibrary.wiley.com/agu/journal/10.1002/(ISSN)1944-7973/", "Impact Factor":"3.709", "Five Year IF":3.448, "IF Year":2013, "H Index":0, "Discipline 1":"Water Policy", "Discipline 2":0, "Discipline 3":0, "Discipline 4":0, "Word Count":"Abstract= 250", "Date Uploaded":0, "Open Access Status":"No", "Open Access Comments":0, "Water Institute Published Status":"No", "Contacts":0, "Additional Comments":0},
  "Aqua- Journal of Water Supply: Research and Technology": { "Publisher":0, "Journal URL":"http://www.iwaponline.com/jws/", "Impact Factor":"0.521", "Five Year IF":0 (new), "IF Year":2013, "H Index":0, "Discipline 1":"Water Policy", "Discipline 2":0, "Discipline 3":0, "Discipline 4":0, "Word Count":"", "Date Uploaded":0, "Open Access Status":"Yes", "Open Access Comments":0, "Water Institute Published Status":"Yes", "Contacts":0, "Additional Comments":0},
  "Irrigation and Drainage": { "Publisher":0, "Journal URL":"http://onlinelibrary.wiley.com/journal/10.1002/(ISSN)1531-0361", "Impact Factor":"0.717", "Five Year IF":1.1, "IF Year":2013, "H Index":0, "Discipline 1":"Water Policy", "Discipline 2":0, "Discipline 3":0, "Discipline 4":0, "Word Count":"Manuscript= 6000", "Date Uploaded":0, "Open Access Status":"Yes", "Open Access Comments":0, "Water Institute Published Status":"No", "Contacts":0, "Additional Comments":0},
  "Journal of the American Water Resources Association": { "Publisher":0, "Journal URL":"http://www.awra.org/index.html", "Impact Factor":"2.074", "Five Year IF":2.13, "IF Year":2013, "H Index":0, "Discipline 1":"Water Policy", "Discipline 2":0, "Discipline 3":0, "Discipline 4":0, "Word Count":"Uploaded manuscript= 10mb Abstract= 1500", "Date Uploaded":0, "Open Access Status":"No", "Open Access Comments":0, "Water Institute Published Status":"No", "Contacts":0, "Additional Comments":0},
  "Journal of Water and Climate Change": { "Publisher":0, "Journal URL":"http://www.iwaponline.com/jwc/", "Impact Factor":"1.044", "Five Year IF":1, "IF Year":2013, "H Index":0, "Discipline 1":"Water Policy", "Discipline 2":0, "Discipline 3":0, "Discipline 4":0, "Word Count":"", "Date Uploaded":0, "Open Access Status":"No", "Open Access Comments":0, "Water Institute Published Status":"Yes", "Contacts":0, "Additional Comments":0},
  "Journal of Water Sanitation and Hygiene for Development": { "Publisher":0, "Journal URL":"http://www.iwaponline.com/washdev/", "Impact Factor":"0.509", "Five Year IF":0, "IF Year":2013, "H Index":0, "Discipline 1":"Water Policy", "Discipline 2":0, "Discipline 3":0, "Discipline 4":0, "Word Count":"", "Date Uploaded":0, "Open Access Status":"Yes", "Open Access Comments":0, "Water Institute Published Status":"Yes", "Contacts":0, "Additional Comments":0},
  "Journal of Water Supply: Research & Technology - AQUA": { "Publisher":0, "Journal URL":"http://www.iwaponline.com/jws/", "Impact Factor":"0.521", "Five Year IF":0.775, "IF Year":2013, "H Index":0, "Discipline 1":"Water Policy ", "Discipline 2":0, "Discipline 3":0, "Discipline 4":0, "Word Count":"manuscripts= 10,000", "Date Uploaded":0, "Open Access Status":"Yes", "Open Access Comments":0, "Water Institute Published Status":"No", "Contacts":0, "Additional Comments":0},
  "Rural Water Supply Network": { "Publisher":0, "Journal URL":"http://www.rural-water-supply.net/en/", "Impact Factor":"N/A", "Five Year IF":0, "IF Year":2013, "H Index":0, "Discipline 1":"Water Policy ", "Discipline 2":0, "Discipline 3":0, "Discipline 4":0, "Word Count":"", "Date Uploaded":0, "Open Access Status":"No", "Open Access Comments":0, "Water Institute Published Status":"No", "Contacts":0, "Additional Comments":0},
  "Water - SUI": { "Publisher":0, "Journal URL":"http://www.mdpi.com/journal/water", "Impact Factor":"1.291", "Five Year IF":0.991, "IF Year":2013, "H Index":0, "Discipline 1":"Water Policy ", "Discipline 2":0, "Discipline 3":0, "Discipline 4":0, "Word Count":"Abstract= 200", "Date Uploaded":0, "Open Access Status":"Yes", "Open Access Comments":0, "Water Institute Published Status":"No", "Contacts":0, "Additional Comments":0},
  "Water Environment Research": { "Publisher":0, "Journal URL":"http://www.ingentaconnect.com/content/wef/wer", "Impact Factor":"1", "Five Year IF":1, "IF Year":2013, "H Index":0, "Discipline 1":"Water Policy ", "Discipline 2":0, "Discipline 3":0, "Discipline 4":0, "Word Count":"Abstracts= 150 Manuscripts= 4000", "Date Uploaded":0, "Open Access Status":"Yes", "Open Access Comments":0, "Water Institute Published Status":"Yes", "Contacts":0, "Additional Comments":0},
  "Water International": { "Publisher":0, "Journal URL":"http://www.tandfonline.com/loi/rwin20#.U_3gfrywLOM", "Impact Factor":"0.639", "Five Year IF":0.679, "IF Year":2013, "H Index":0, "Discipline 1":"Water Policy ", "Discipline 2":0, "Discipline 3":0, "Discipline 4":0, "Word Count":"Research article= 8500 abstract=100", "Date Uploaded":0, "Open Access Status":"No", "Open Access Comments":0, "Water Institute Published Status":"No", "Contacts":0, "Additional Comments":0},
  "Water Policy": { "Publisher":0, "Journal URL":"http://www.iwaponline.com/wp/", "Impact Factor":"0.867", "Five Year IF":1.42, "IF Year":2013, "H Index":27, "Discipline 1":"Water Policy ", "Discipline 2":0, "Discipline 3":0, "Discipline 4":0, "Word Count":"Manuscript= 8000", "Date Uploaded":0, "Open Access Status":"No ", "Open Access Comments":0, "Water Institute Published Status":"Yes", "Contacts":0, "Additional Comments":0},
  "Water Practice and Technology": { "Publisher":0, "Journal URL":"http://www.iwaponline.com/wpt/", "Impact Factor":"N/A", "Five Year IF":0, "IF Year":2013, "H Index":0, "Discipline 1":"Water Policy ", "Discipline 2":0, "Discipline 3":0, "Discipline 4":0, "Word Count":"", "Date Uploaded":0, "Open Access Status":"No ", "Open Access Comments":0, "Water Institute Published Status":"No", "Contacts":0, "Additional Comments":0},
  "Water Science and Technology: Water Supply": { "Publisher":0, "Journal URL":"http://www.iwaponline.com/ws/", "Impact Factor":"N/A", "Five Year IF":0, "IF Year":2013, "H Index":0, "Discipline 1":"Water Policy ", "Discipline 2":0, "Discipline 3":0, "Discipline 4":0, "Word Count":"Manuscript= 8000 abstract= 200", "Date Uploaded":0, "Open Access Status":"Yes", "Open Access Comments":0, "Water Institute Published Status":"No", "Contacts":0, "Additional Comments":0},
  "Water Utility Management International": { "Publisher":0, "Journal URL":"http://www.iwaponline.com/wumi/", "Impact Factor":"N/A", "Five Year IF":0, "IF Year":2013, "H Index":0, "Discipline 1":"Water Policy ", "Discipline 2":0, "Discipline 3":0, "Discipline 4":0, "Word Count":"", "Date Uploaded":0, "Open Access Status":"No", "Open Access Comments":0, "Water Institute Published Status":"No", "Contacts":0, "Additional Comments":0},
  "Journal of Urban Technology": { "Publisher":0, "Journal URL":"http://www.tandfonline.com/loi/cjut20#.U_3oNrywLOM", "Impact Factor":"0.729", "Five Year IF":0.56, "IF Year":2013, "H Index":0, "Discipline 1":"Water Policy ", "Discipline 2":0, "Discipline 3":0, "Discipline 4":0, "Word Count":"Manuscript= 8000 abstract= 100", "Date Uploaded":0, "Open Access Status":"Yes", "Open Access Comments":0, "Water Institute Published Status":"No", "Contacts":0, "Additional Comments":0},
  "Journal of Water and Health": { "Publisher":0, "Journal URL":"http://www.iwaponline.com/jwh/", "Impact Factor":"1.172", "Five Year IF":1.542, "IF Year":2013, "H Index":0, "Discipline 1":"Water Policy ", "Discipline 2":0, "Discipline 3":0, "Discipline 4":0, "Word Count":"Research= 7500", "Date Uploaded":0, "Open Access Status":"Yes", "Open Access Comments":0, "Water Institute Published Status":"Yes", "Contacts":0, "Additional Comments":0},
  "Journal of Water Quality Exposure and Health": { "Publisher":0, "Journal URL":"http://link.springer.com/journal/12403", "Impact Factor":"N/A", "Five Year IF":1.54, "IF Year":2013, "H Index":0, "Discipline 1":"Water Policy ", "Discipline 2":0, "Discipline 3":0, "Discipline 4":0, "Word Count":"manuscripts= 10,000", "Date Uploaded":0, "Open Access Status":"Yes", "Open Access Comments":0, "Water Institute Published Status":"No", "Contacts":0, "Additional Comments":0},
  "Journal of Water Resources Planning and Management": { "Publisher":0, "Journal URL":"http://ascelibrary.org/journal/jwrmd5", "Impact Factor":"1.76", "Five Year IF":1.757, "IF Year":2013, "H Index":0, "Discipline 1":"Water Policy ", "Discipline 2":0, "Discipline 3":0, "Discipline 4":0, "Word Count":"manuscripts= 10,000", "Date Uploaded":0, "Open Access Status":"Yes", "Open Access Comments":0, "Water Institute Published Status":"No", "Contacts":0, "Additional Comments":0},
  "Journal American Water Works Association": { "Publisher":0, "Journal URL":"http://www.awwa.org/publications/journal-awwa.aspx", "Impact Factor":"0.516", "Five Year IF":0, "IF Year":2013, "H Index":0, "Discipline 1":"", "Discipline 2":0, "Discipline 3":0, "Discipline 4":0, "Word Count":"", "Date Uploaded":0, "Open Access Status":"No ", "Open Access Comments":0, "Water Institute Published Status":"", "Contacts":0, "Additional Comments":0},
  "Journal of Environmental and Public Health": { "Publisher":0, "Journal URL":"http://www.hindawi.com/journals/jeph/", "Impact Factor":"N/A", "Five Year IF":0, "IF Year":2013, "H Index":18, "Discipline 1":"", "Discipline 2":0, "Discipline 3":0, "Discipline 4":0, "Word Count":"Abstracts= 200", "Date Uploaded":0, "Open Access Status":"Yes", "Open Access Comments":0, "Water Institute Published Status":"No", "Contacts":0, "Additional Comments":0},
  "Journal of Hydrology": { "Publisher":0, "Journal URL":"http://www.journals.elsevier.com/journal-of-hydrology/", "Impact Factor":"2.693", "Five Year IF":0, "IF Year":2013, "H Index":0, "Discipline 1":"", "Discipline 2":0, "Discipline 3":0, "Discipline 4":0, "Word Count":"", "Date Uploaded":0, "Open Access Status":"Yes", "Open Access Comments":Can pay fee to make it totally OA, "Water Institute Published Status":"", "Contacts":0, "Additional Comments":0},
  "Journal of Planning Education and Research": { "Publisher":0, "Journal URL":"http://jpe.sagepub.com/", "Impact Factor":"1.511", "Five Year IF":1.71, "IF Year":2013, "H Index":0, "Discipline 1":"", "Discipline 2":0, "Discipline 3":0, "Discipline 4":0, "Word Count":"Manuscript= 10 pages", "Date Uploaded":0, "Open Access Status":"Yes", "Open Access Comments":0, "Water Institute Published Status":"No", "Contacts":0, "Additional Comments":0},
  "Journal of Policy Analysis and Management": { "Publisher":0, "Journal URL":"http://onlinelibrary.wiley.com/journal/10.1002/(ISSN)1520-6688", "Impact Factor":"2.101", "Five Year IF":0.168, "IF Year":2013, "H Index":0, "Discipline 1":"", "Discipline 2":0, "Discipline 3":0, "Discipline 4":0, "Word Count":"Manuscript= 30 pages", "Date Uploaded":0, "Open Access Status":"Yes", "Open Access Comments":0, "Water Institute Published Status":"No", "Contacts":0, "Additional Comments":0},
  "Philosophical Transactions of the Royal Society A": { "Publisher":0, "Journal URL":"http://rsta.royalsocietypublishing.org/", "Impact Factor":"2.864", "Five Year IF":0, "IF Year":2013, "H Index":0, "Discipline 1":"", "Discipline 2":0, "Discipline 3":0, "Discipline 4":0, "Word Count":"", "Date Uploaded":0, "Open Access Status":"Yes", "Open Access Comments":0, "Water Institute Published Status":"", "Contacts":0, "Additional Comments":0},
  "Philosophical Transactions of the Royal Society B": { "Publisher":0, "Journal URL":"http://rstb.royalsocietypublishing.org/", "Impact Factor":"6.314", "Five Year IF":0, "IF Year":2013, "H Index":0, "Discipline 1":"", "Discipline 2":0, "Discipline 3":0, "Discipline 4":0, "Word Count":"", "Date Uploaded":0, "Open Access Status":"Yes", "Open Access Comments":After 1 year of publication, "Water Institute Published Status":"", "Contacts":0, "Additional Comments":0},
  "PLOS ONE": { "Publisher":0, "Journal URL":"http://www.plosone.org/", "Impact Factor":"3.534", "Five Year IF":4.244, "IF Year":2013, "H Index":0, "Discipline 1":"", "Discipline 2":0, "Discipline 3":0, "Discipline 4":0, "Word Count":"research article= 3002", "Date Uploaded":0, "Open Access Status":"Yes", "Open Access Comments":0, "Water Institute Published Status":"Yes", "Contacts":0, "Additional Comments":0},
  "PNAS": { "Publisher":0, "Journal URL":"http://www.pnas.org/", "Impact Factor":"9.809", "Five Year IF":10.58, "IF Year":2013, "H Index":0, "Discipline 1":"", "Discipline 2":0, "Discipline 3":0, "Discipline 4":0, "Word Count":"Manuscript= 49,000 characters", "Date Uploaded":0, "Open Access Status":"Yes", "Open Access Comments":0, "Water Institute Published Status":"No", "Contacts":0, "Additional Comments":0},
  "The BMJ": { "Publisher":0, "Journal URL":"http://www.bmj.com/thebmj", "Impact Factor":"16.378", "Five Year IF":0, "IF Year":2013, "H Index":0, "Discipline 1":"", "Discipline 2":0, "Discipline 3":0, "Discipline 4":0, "Word Count":"", "Date Uploaded":0, "Open Access Status":"Yes", "Open Access Comments":Archived articles only, "Water Institute Published Status":"", "Contacts":0, "Additional Comments":0},
  "Water Alternatives": { "Publisher":0, "Journal URL":"http://www.water-alternatives.org/", "Impact Factor":"N/A", "Five Year IF":0, "IF Year":2013, "H Index":0, "Discipline 1":"", "Discipline 2":0, "Discipline 3":0, "Discipline 4":0, "Word Count":"", "Date Uploaded":0, "Open Access Status":"Yes", "Open Access Comments":0, "Water Institute Published Status":"No", "Contacts":0, "Additional Comments":0},
  "Water and Climate Change": { "Publisher":0, "Journal URL":"http://water.epa.gov/scitech/climatechange/", "Impact Factor":"N/A", "Five Year IF":0, "IF Year":2013, "H Index":0, "Discipline 1":"", "Discipline 2":0, "Discipline 3":0, "Discipline 4":0, "Word Count":"", "Date Uploaded":0, "Open Access Status":"No ", "Open Access Comments":0, "Water Institute Published Status":"No", "Contacts":0, "Additional Comments":0},
  "Water Asset Management International": { "Publisher":0, "Journal URL":"http://www.iwaponline.com/wami/", "Impact Factor":"N/A", "Five Year IF":0, "IF Year":2013, "H Index":0, "Discipline 1":"", "Discipline 2":0, "Discipline 3":0, "Discipline 4":0, "Word Count":"", "Date Uploaded":0, "Open Access Status":"No ", "Open Access Comments":0, "Water Institute Published Status":"No", "Contacts":0, "Additional Comments":0},
  "Water Treatment and Human Health": { "Publisher":0, "Journal URL":"http://www.mdpi.com/journal/water/special_issues/water-health", "Impact Factor":"N/A (new)", "Five Year IF":0, "IF Year":2013, "H Index":0, "Discipline 1":"", "Discipline 2":0, "Discipline 3":0, "Discipline 4":0, "Word Count":"", "Date Uploaded":0, "Open Access Status":"Yes", "Open Access Comments":0, "Water Institute Published Status":"", "Contacts":0, "Additional Comments":0},
  "Habitat International": { "Publisher":0, "Journal URL":"http://www.journals.elsevier.com/habitat-international/", "Impact Factor":"1.746", "Five Year IF":1.946, "IF Year":2014, "H Index":0, "Discipline 1":"Environmental Studies", "Discipline 2":Planning & Development, "Discipline 3":Urban Studies, "Discipline 4":0, "Word Count":"articles should not exceed 6,000 words unless there is special justification", "Date Uploaded":7/31/15, "Open Access Status":"Yes", "Open Access Comments":fee, "Water Institute Published Status":"", "Contacts":0, "Additional Comments":0},
  "Water Quality, Exposure and Health": { "Publisher":Springer, "Journal URL":"http://www.springer.com/environment/pollution+and+remediation/journal/12403", "Impact Factor":"0.912", "Five Year IF":0.955, "IF Year":2014, "H Index":0, "Discipline 1":"Water Resources", "Discipline 2":0, "Discipline 3":0, "Discipline 4":0, "Word Count":"", "Date Uploaded":8/17/15, "Open Access Status":"Yes", "Open Access Comments":Springer , "Water Institute Published Status":"", "Contacts":0, "Additional Comments":0},
  "Water History": { "Publisher":Springer, "Journal URL":"http://link.springer.com/journal/12685", "Impact Factor":"1.081", "Five Year IF":0, "IF Year":2014, "H Index":0, "Discipline 1":"Civil Engineering", "Discipline 2":Hydrogeology, "Discipline 3":Pollution and Remediation, "Discipline 4":Water, "Word Count":"", "Date Uploaded":10/13/15, "Open Access Status":"Yes", "Open Access Comments":Springer , "Water Institute Published Status":"", "Contacts":0, "Additional Comments":0},
  "Journal of Development Effectiveness": { "Publisher":Taylor & Francis, "Journal URL":"http://www.tandfonline.com/loi/rjde20#.Vm8vdhorK34", "Impact Factor":"1.327", "Five Year IF":1.26, "IF Year":2014, "H Index":0, "Discipline 1":"Planning & Development", "Discipline 2":0, "Discipline 3":0, "Discipline 4":0, "Word Count":"manuscript = 8000 words including references, footnotes and endnotes", "Date Uploaded":12/14/15, "Open Access Status":"Yes", "Open Access Comments":T&F/Routledge , "Water Institute Published Status":"", "Contacts":0, "Additional Comments":0}
}